exfill/__init__.py
exfill/config.ini
exfill/extractor.py
exfill/parsers/__init__.py
exfill/parsers/linkedin_parser.py
exfill/parsers/parser_base.py
exfill/parsers/parser_factory.py
exfill/scrapers/__init__.py
exfill/scrapers/linkedin_scraper.py
exfill/scrapers/scraper_base.py
exfill/scrapers/scraper_factory.py
exfill/support/geckodriver
exfill-0.1.29.dist-info/entry_points.txt
exfill-0.1.29.dist-info/WHEEL
exfill-0.1.29.dist-info/METADATA
exfill-0.1.29.dist-info/RECORD
