Metadata-Version: 2.1
Name: exfill
Version: 0.1.29
Summary: A small app to grab job postings from online job boards
Home-page: https://github.com/jay-law/job-scraper
Author: jay-law
Author-email: jay-law@users.noreply.github.com
Requires-Python: >=3.8,<4.0
Classifier: Programming Language :: Python :: 3
Classifier: Programming Language :: Python :: 3.10
Classifier: Programming Language :: Python :: 3.8
Classifier: Programming Language :: Python :: 3.9
Requires-Dist: bs4 (>=0.0.1,<0.0.2)
Requires-Dist: selenium (>=4.1.5,<5.0.0)
Requires-Dist: setuptools-scm (>=6.4.2,<7.0.0)
Project-URL: Documentation, https://github.com/jay-law/job-scraper
Project-URL: Repository, https://github.com/jay-law/job-scraper
